[
  {
    "id": "49e6fe9c14ed777a",
    "type": "tab",
    "label": "VPS - Abdellah Irrigation Logic",
    "disabled": false,
    "info": "v3 — All 6 events sent: DAY_STARTED, STOP_DAY, START_IRRIGATION, IRRIGATION_DONE, REPOS_START, REPOS_DONE"
  },
  {
    "id": "d4859caa8caa9806",
    "type": "function",
    "z": "49e6fe9c14ed777a",
    "name": "Store flow vars + fanout",
    "func": "const d = msg.payload;\n\nflow.set('last_weight_g',     d.weight_g     || 0);\nflow.set('last_pct_drainage', d.pct_drainage || 0);\nflow.set('last_ec',           d.ec_mscm      || 0);\nflow.set('last_ph',           d.ph           || 0);\nflow.set('last_input_mL',     d.input_mL     || 0);\nflow.set('last_drainage_mL',  d.drainage_mL  || 0);\nflow.set('last_temp',         d.temp         || 0);\nflow.set('pump_state',        d.pump         || 'OFF');\nflow.set('drain_pump_state',  d.drain_pump   || 'OFF');\n\nnode.status({ fill:'blue', shape:'dot',\n    text: `drain:${d.pct_drainage}% EC:${d.ec_mscm} w:${d.weight_g}g` });\n\nreturn msg;",
    "outputs": 1,
    "timeout": "",
    "noerr": 0,
    "initialize": "",
    "finalize": "",
    "libs": [],
    "x": 150,
    "y": 240,
    "wires": [["eca57154dd4bf420", "401acfb961788c26", "0c79e7a74668ea01"]]
  },
  {
    "id": "eca57154dd4bf420",
    "type": "link out",
    "z": "49e6fe9c14ed777a",
    "name": "→ Storage: sensors",
    "mode": "link",
    "links": ["27fded223923fa54"],
    "x": 315,
    "y": 200,
    "wires": []
  },
  {
    "id": "401acfb961788c26",
    "type": "function",
    "z": "49e6fe9c14ed777a",
    "name": "🚦 Gate: only pass if irrigation_active",
    "func": "const active       = flow.get('irrigation_active') || false;\nconst waitingRepos = flow.get('waiting_for_repos') || false;\nconst dayDone      = flow.get('day_done')          || false;\n\nif (!active) {\n    node.status({ fill:'grey', shape:'ring', text:'Not active — waiting morning check' });\n    return null;\n}\nif (dayDone) {\n    node.status({ fill:'green', shape:'ring', text:'Day complete — no more tours' });\n    return null;\n}\nif (waitingRepos) {\n    node.status({ fill:'yellow', shape:'ring', text:'In repos — waiting for timer...' });\n    return null;\n}\n\nnode.status({ fill:'green', shape:'dot', text:'✅ Passing to scheduler' });\nreturn msg;",
    "outputs": 1,
    "x": 450,
    "y": 240,
    "wires": [["3d5b054e96a86894"]]
  },
  {
    "id": "3d5b054e96a86894",
    "type": "function",
    "z": "49e6fe9c14ed777a",
    "name": "Irrigation Scheduler",
    "func": "const pct    = msg.payload.pct_drainage;\nconst ec     = msg.payload.ec_mscm;\nconst tour   = (flow.get('tour_count') || 0) + 1;\nconst EC_MAX = 5.0;\nconst TEST_MODE = true;\n\nif (pct >= 20 && tour > 8) {\n    flow.set('weight_lastEvening', msg.payload.weight_g);\n    flow.set('tour_count', 0);\n    flow.set('irrigation_active', false);\n    flow.set('waiting_for_repos', false);\n    flow.set('day_done', true);\n    node.status({ fill:'green', shape:'ring',\n        text: `Day done — tour ${tour} — weight saved ${msg.payload.weight_g}g` });\n    return [null, { payload: {\n        action: 'STOP_DAY',\n        timestamp: new Date().toISOString()\n    }}];\n}\n\nlet duree, repos, zone;\n\nif (TEST_MODE) {\n    if (pct < 10)       { duree = 1; repos = 1; zone = 'Zone1 <10% [TEST]'; }\n    else if (pct < 20)  { duree = 1; repos = tour <= 3 ? 1 : 2; zone = 'Zone2 10-20% [TEST]'; }\n    else if (pct < 35)  { duree = 1; repos = 2; zone = 'Zone3 20-35% [TEST]'; }\n    else {\n        duree = 1;\n        repos = ({6:2,7:2,8:2,9:2})[tour] || 2;\n        zone = 'Zone4 >=35% [TEST]';\n    }\n} else {\n    if (pct < 10)       { duree = 15; repos = 1; zone = 'Zone1 <10%'; }\n    else if (pct < 20)  { duree = 10; repos = tour <= 3 ? 5 : 10; zone = 'Zone2 10-20%'; }\n    else if (pct < 35)  { duree = 8;  repos = 15; zone = 'Zone3 20-35%'; }\n    else {\n        duree = 8;\n        repos = ({6:19,7:24,8:29,9:34})[tour] || 34;\n        zone = 'Zone4 >=35%';\n    }\n}\n\nlet ec_adj = '';\nif (ec > EC_MAX) {\n    if (!TEST_MODE) { duree = Math.max(5, duree - 1); ec_adj = ` (EC ${ec}>${EC_MAX} → -1min)`; }\n    else            { ec_adj = ` (EC ${ec}>${EC_MAX} — no adj in TEST)`; }\n}\n\nflow.set('tour_count', tour);\nflow.set('current_duree', duree);\nflow.set('current_repos', repos);\nflow.set('waiting_for_repos', true);\n\nnode.status({ fill:'green', shape:'dot',\n    text: `Tour ${tour} | ${zone} | ${duree}min irr | ${repos}min repos${ec_adj}` });\n\nmsg.payload = {\n    action: 'START_IRRIGATION',\n    tour, zone,\n    duree_min: duree,\n    repos_min: repos,\n    pct_drainage: pct,\n    ec_mscm: ec,\n    ec_adjusted: ec > EC_MAX,\n    test_mode: TEST_MODE,\n    timestamp: new Date().toISOString()\n};\n\n// Output 1 → pump chain | Output 2 → events storage\nreturn [msg, { payload: { action: 'START_IRRIGATION', timestamp: msg.payload.timestamp } }];",
    "outputs": 2,
    "timeout": "",
    "noerr": 0,
    "initialize": "",
    "finalize": "",
    "libs": [],
    "x": 730,
    "y": 240,
    "wires": [["9407a136b86d9964"], ["c88c8b3454a35491"]]
  },
  {
    "id": "9407a136b86d9964",
    "type": "function",
    "z": "49e6fe9c14ed777a",
    "name": "Build Pump ON command",
    "func": "const duree = msg.payload.duree_min || flow.get('current_duree');\nconst repos = msg.payload.repos_min || flow.get('current_repos');\nconst tour  = flow.get('tour_count');\n\nmsg._duree_min = duree;\nmsg._repos_min = repos;\nmsg._tour      = tour;\nmsg.payload    = { id: 'abdellah', pump: 1 };\n\nnode.status({ fill:'green', shape:'dot', text: `Pump ON — ${duree}min tour ${tour}` });\nreturn msg;",
    "outputs": 1,
    "timeout": "",
    "noerr": 0,
    "initialize": "",
    "finalize": "",
    "libs": [],
    "x": 770,
    "y": 180,
    "wires": [["cbec5321b0a0b89d", "48fc44b7806a9435"]]
  },
  {
    "id": "cbec5321b0a0b89d",
    "type": "function",
    "z": "49e6fe9c14ed777a",
    "name": "💧 Pump OFF Timer + Countdown",
    "func": "const duree_min = msg._duree_min || flow.get('current_duree') || 1;\nconst repos_min = msg._repos_min || flow.get('current_repos') || 1;\nconst tour      = msg._tour      || flow.get('tour_count')    || 1;\nconst startedAt = Date.now();\n\nconst old = context.get('pumpOffTimer');\nif (old) clearInterval(old);\n\nnode.status({ fill:'yellow', shape:'dot', text: `💧 Pump ON — ${duree_min}min | tour ${tour}` });\n\nconst tick = setInterval(() => {\n    const elapsed_s   = Math.floor((Date.now() - startedAt) / 1000);\n    const remaining_s = Math.max(0, duree_min * 60 - elapsed_s);\n    const mins        = Math.floor(remaining_s / 60);\n    const secs        = remaining_s % 60;\n    const pct_done    = Math.min(100, Math.round((elapsed_s / (duree_min * 60)) * 100));\n\n    node.send([null, {\n        payload: {\n            type: 'irrigation', remaining_s, elapsed_s,\n            total_s: duree_min * 60, pct_done,\n            fmt: `${mins}:${String(secs).padStart(2,'0')}`,\n            pump: 'ON', tour\n        }\n    }]);\n\n    node.status({ fill:'green', shape:'dot',\n        text: `💧 ${mins}:${String(secs).padStart(2,'0')} left | tour ${tour}` });\n\n    if (remaining_s <= 0) {\n        clearInterval(tick);\n        context.set('pumpOffTimer', null);\n        node.status({ fill:'red', shape:'ring', text: `Pump OFF — starting repos ${repos_min}min` });\n\n        node.send([{ topic: 'pump_off', payload: { id: 'abdellah', pump: 0 } }, null]);\n        setTimeout(() => {\n            node.send([{\n                topic: 'repos_start',\n                payload: { action: 'IRRIGATION_DONE', tour, repos_min, timestamp: new Date().toISOString() }\n            }, null]);\n        }, 500);\n    }\n}, 1000);\n\ncontext.set('pumpOffTimer', tick);\nreturn null;",
    "outputs": 2,
    "timeout": "",
    "noerr": 0,
    "initialize": "",
    "finalize": "",
    "libs": [],
    "x": 1060,
    "y": 180,
    "wires": [["fd58979fb782450b"], ["abe89c1c16fb14ef"]]
  },
  {
    "id": "abe89c1c16fb14ef",
    "type": "function",
    "z": "49e6fe9c14ed777a",
    "name": "Throttle 5s",
    "func": "const now = Date.now();\nconst last = context.get('lastSent') || 0;\nif (now - last < 5000) return null;\ncontext.set('lastSent', now);\nreturn msg;",
    "outputs": 1,
    "x": 1030,
    "y": 240,
    "wires": [["727ec4f83c9930a4"]]
  },
  {
    "id": "fd58979fb782450b",
    "type": "function",
    "z": "49e6fe9c14ed777a",
    "name": "Route: pump OFF or repos start",
    "func": "if (msg.topic === 'pump_off') {\n    node.status({ fill:'red', shape:'dot', text:'Pump OFF → HTTP' });\n    return [msg, null];\n} else if (msg.topic === 'repos_start') {\n    node.status({ fill:'blue', shape:'dot', text:'Repos start → timer' });\n    return [null, msg];\n}\nreturn null;",
    "outputs": 2,
    "x": 1310,
    "y": 120,
    "wires": [["64a57998e851346c"], ["d22d6b2e07e7d0a0"]]
  },
  {
    "id": "d22d6b2e07e7d0a0",
    "type": "function",
    "z": "49e6fe9c14ed777a",
    "name": "⏳ Repos Timer + Countdown",
    "func": "const repos_min = msg.payload.repos_min || flow.get('current_repos') || 1;\nconst tour      = msg.payload.tour      || flow.get('tour_count')    || 1;\nconst startedAt = Date.now();\n\nconst old = context.get('reposTimer');\nif (old) clearInterval(old);\n\nnode.status({ fill:'grey', shape:'ring', text: `⏳ Repos ${repos_min}min — after tour ${tour}` });\n\n// Emit REPOS_START event immediately\nnode.send([{ payload: {\n    action: 'REPOS_START',\n    timestamp: new Date().toISOString()\n}}, null]);\n\nconst tick = setInterval(() => {\n    const elapsed_s   = Math.floor((Date.now() - startedAt) / 1000);\n    const remaining_s = Math.max(0, repos_min * 60 - elapsed_s);\n    const mins        = Math.floor(remaining_s / 60);\n    const secs        = remaining_s % 60;\n    const pct_done    = Math.min(100, Math.round((elapsed_s / (repos_min * 60)) * 100));\n\n    node.send([null, {\n        payload: {\n            type: 'repos', remaining_s, elapsed_s,\n            total_s: repos_min * 60, pct_done,\n            fmt: `${mins}:${String(secs).padStart(2,'0')}`,\n            pump: 'OFF', tour, next_tour: tour + 1\n        }\n    }]);\n\n    node.status({ fill:'yellow', shape:'ring',\n        text: `⏳ ${mins}:${String(secs).padStart(2,'0')} → tour ${tour + 1}` });\n\n    if (remaining_s <= 0) {\n        clearInterval(tick);\n        context.set('reposTimer', null);\n        flow.set('waiting_for_repos', false);\n        node.status({ fill:'blue', shape:'dot', text: `✅ Repos done — tour ${tour + 1} ready` });\n        // Emit REPOS_DONE event\n        node.send([{ payload: {\n            action: 'REPOS_DONE',\n            timestamp: new Date().toISOString()\n        }}, null]);\n    }\n}, 1000);\n\ncontext.set('reposTimer', tick);\nreturn null;",
    "outputs": 2,
    "timeout": "",
    "noerr": 0,
    "initialize": "",
    "finalize": "",
    "libs": [],
    "x": 1410,
    "y": 180,
    "wires": [["dea362d54e7aa633"], ["78e9d38739ec1cca"]]
  },
  {
    "id": "78e9d38739ec1cca",
    "type": "function",
    "z": "49e6fe9c14ed777a",
    "name": "Throttle 5s",
    "func": "const now = Date.now();\nconst last = context.get('lastSent') || 0;\nif (now - last < 5000) return null;\ncontext.set('lastSent', now);\nreturn msg;",
    "outputs": 1,
    "x": 1650,
    "y": 200,
    "wires": [["59e46eeafb4febf7"]]
  },
  {
    "id": "59e46eeafb4febf7",
    "type": "link out",
    "z": "49e6fe9c14ed777a",
    "name": "→ Storage: timers",
    "mode": "link",
    "links": ["f28944618417ca67"],
    "x": 1795,
    "y": 200,
    "wires": []
  },
  {
    "id": "7ea8b530e583bcb9",
    "type": "link out",
    "z": "49e6fe9c14ed777a",
    "name": "→ Storage: events",
    "mode": "link",
    "links": ["2270ef4036fd5678"],
    "x": 1785,
    "y": 460,
    "wires": []
  },
  {
    "id": "0c79e7a74668ea01",
    "type": "function",
    "z": "49e6fe9c14ed777a",
    "name": "🚰 Drainage Logic (5L threshold)",
    "func": "const drainage_mL  = msg.payload.drainage_mL || 0;\nconst THRESHOLD_ML = 5000;\nconst drainRunning = flow.get('drain_pump_running') || false;\n\nif (drainage_mL >= THRESHOLD_ML && !drainRunning) {\n    flow.set('drain_pump_running', true);\n    node.status({ fill:'blue', shape:'dot',\n        text: `🚰 Drain ON — ${drainage_mL}mL >= ${THRESHOLD_ML}mL` });\n    return [{ payload: { id: 'abdellah', drain_pump: 1 } }, null];\n}\n\nnode.status({ fill:'grey', shape:'ring',\n    text: `drain: ${drainage_mL}mL` });\nreturn null;",
    "outputs": 2,
    "x": 440,
    "y": 280,
    "wires": [["c8b3d887916f1d4f"], []]
  },
  {
    "id": "c8b3d887916f1d4f",
    "type": "function",
    "z": "49e6fe9c14ed777a",
    "name": "⏱️ Drain Pump OFF Timer (3min)",
    "func": "const DRAIN_DURATION_MIN = 3;\nconst old = context.get('drainOffTimer');\nif (old) clearTimeout(old);\n\nnode.status({ fill:'blue', shape:'dot',\n    text: `🚰 Drain ON — auto OFF in ${DRAIN_DURATION_MIN}min` });\n\nnode.send({ payload: msg.payload });\n\nconst timer = setTimeout(() => {\n    context.set('drainOffTimer', null);\n    flow.set('drain_pump_running', false);\n    node.status({ fill:'grey', shape:'ring', text:'🚰 Drain pump OFF' });\n    node.send({ payload: { id: 'abdellah', drain_pump: 0 } });\n}, DRAIN_DURATION_MIN * 60 * 1000);\n\ncontext.set('drainOffTimer', timer);\nreturn null;",
    "outputs": 1,
    "x": 440,
    "y": 340,
    "wires": [["6fb9bcb3a595b36f"]]
  },
  {
    "id": "26fc7d4d6be78a9d",
    "type": "inject",
    "z": "49e6fe9c14ed777a",
    "name": "Morning check (7:50 AM)",
    "repeat": "",
    "crontab": "50 07 * * *",
    "once": false,
    "payload": "{}",
    "payloadType": "json",
    "x": 160,
    "y": 500,
    "wires": [["412e774b8c52ac74"]]
  },
  {
    "id": "412e774b8c52ac74",
    "type": "function",
    "z": "49e6fe9c14ed777a",
    "name": "Morning Weight Check",
    "func": "const weightEvening = flow.get('weight_lastEvening') || null;\nconst weightMorning  = flow.get('last_weight_g')     || null;\n\nif (!weightEvening || !weightMorning) {\n    node.warn('No reference weight yet — skipping morning check');\n    node.status({ fill:'yellow', shape:'ring', text:'No reference weight' });\n    return null;\n}\n\nconst delta = weightEvening - weightMorning;\nconst threshold = weightEvening * 0.05;\nconst shouldIrrigate = delta >= threshold;\n\nnode.status({\n    fill: shouldIrrigate ? 'green' : 'grey', shape: 'dot',\n    text: `Δ=${delta}g | thr=${Math.round(threshold)}g | ${shouldIrrigate ? 'START' : 'WAIT'}`\n});\n\nmsg.payload = {\n    weight_evening_g: weightEvening,\n    weight_morning_g: weightMorning,\n    delta_g: delta,\n    threshold_g: Math.round(threshold),\n    should_irrigate: shouldIrrigate,\n    timestamp: new Date().toISOString()\n};\nreturn msg;",
    "outputs": 1,
    "x": 410,
    "y": 500,
    "wires": [["971e0a1a8779652d"]]
  },
  {
    "id": "971e0a1a8779652d",
    "type": "switch",
    "z": "49e6fe9c14ed777a",
    "name": "Should irrigate?",
    "property": "payload.should_irrigate",
    "propertyType": "msg",
    "rules": [
      {
        "t": "true"
      },
      {
        "t": "false"
      }
    ],
    "checkall": "true",
    "outputs": 2,
    "x": 640,
    "y": 500,
    "wires": [["791f6e2e7b43ab98"], []]
  },
  {
    "id": "791f6e2e7b43ab98",
    "type": "function",
    "z": "49e6fe9c14ed777a",
    "name": "Reset Tour Counter + Unlock Gate",
    "func": "flow.set('tour_count', 0);\nflow.set('irrigation_active', true);\nflow.set('waiting_for_repos', false);\nflow.set('day_done', false);\n\nnode.status({ fill:'green', shape:'dot', text:'Day started — gate open' });\nmsg.payload = { action: 'DAY_STARTED', timestamp: new Date().toISOString() };\nreturn msg;",
    "outputs": 1,
    "timeout": "",
    "noerr": 0,
    "initialize": "",
    "finalize": "",
    "libs": [],
    "x": 900,
    "y": 500,
    "wires": [["5fc533b6ccc2c311"]]
  },
  {
    "id": "13ad297d857525c8",
    "type": "mqtt in",
    "z": "49e6fe9c14ed777a",
    "name": "",
    "topic": " irrigation/abdellah/data",
    "qos": "1",
    "datatype": "auto-detect",
    "broker": "4df1d8fb6c6e0939",
    "nl": false,
    "rap": true,
    "rh": 0,
    "inputs": 0,
    "x": 120,
    "y": 160,
    "wires": [["d4859caa8caa9806"]]
  },
  {
    "id": "48fc44b7806a9435",
    "type": "mqtt out",
    "z": "49e6fe9c14ed777a",
    "name": "",
    "topic": "irrigation/abdellah/cmd",
    "qos": "1",
    "retain": "",
    "respTopic": "",
    "contentType": "",
    "userProps": "",
    "correl": "",
    "expiry": "",
    "broker": "0a6617d532e66960",
    "x": 1000,
    "y": 120,
    "wires": []
  },
  {
    "id": "64a57998e851346c",
    "type": "mqtt out",
    "z": "49e6fe9c14ed777a",
    "name": "",
    "topic": "irrigation/abdellah/cmd",
    "qos": "1",
    "retain": "",
    "respTopic": "",
    "contentType": "",
    "userProps": "",
    "correl": "",
    "expiry": "",
    "broker": "0a6617d532e66960",
    "x": 1600,
    "y": 80,
    "wires": []
  },
  {
    "id": "6fb9bcb3a595b36f",
    "type": "mqtt out",
    "z": "49e6fe9c14ed777a",
    "name": "irrigation/abdellah/cmd",
    "topic": "irrigation/abdellah/cmd",
    "qos": "",
    "retain": "",
    "respTopic": "",
    "contentType": "",
    "userProps": "",
    "correl": "",
    "expiry": "",
    "broker": "0a6617d532e66960",
    "x": 400,
    "y": 400,
    "wires": []
  },
  {
    "id": "c88c8b3454a35491",
    "type": "link out",
    "z": "49e6fe9c14ed777a",
    "name": "irrigation sche",
    "mode": "link",
    "links": ["2fabf47247044f58"],
    "x": 865,
    "y": 240,
    "wires": []
  },
  {
    "id": "2fabf47247044f58",
    "type": "link in",
    "z": "49e6fe9c14ed777a",
    "name": "link in 1",
    "links": ["c88c8b3454a35491"],
    "x": 1645,
    "y": 460,
    "wires": [["7ea8b530e583bcb9"]]
  },
  {
    "id": "dea362d54e7aa633",
    "type": "link out",
    "z": "49e6fe9c14ed777a",
    "name": "repos-timer",
    "mode": "link",
    "links": ["a447ab6896b76872"],
    "x": 1595,
    "y": 160,
    "wires": []
  },
  {
    "id": "a447ab6896b76872",
    "type": "link in",
    "z": "49e6fe9c14ed777a",
    "name": "link in 2",
    "links": ["dea362d54e7aa633"],
    "x": 1635,
    "y": 420,
    "wires": [["7ea8b530e583bcb9"]]
  },
  {
    "id": "5fc533b6ccc2c311",
    "type": "link out",
    "z": "49e6fe9c14ed777a",
    "name": "gate",
    "mode": "link",
    "links": ["35ef01d35ebe421f"],
    "x": 1125,
    "y": 500,
    "wires": []
  },
  {
    "id": "35ef01d35ebe421f",
    "type": "link in",
    "z": "49e6fe9c14ed777a",
    "name": "link in 3",
    "links": ["5fc533b6ccc2c311"],
    "x": 1635,
    "y": 500,
    "wires": [["7ea8b530e583bcb9"]]
  },
  {
    "id": "727ec4f83c9930a4",
    "type": "link out",
    "z": "49e6fe9c14ed777a",
    "name": "thort",
    "mode": "link",
    "links": ["83e4bb7f56c7fb8b"],
    "x": 1155,
    "y": 240,
    "wires": []
  },
  {
    "id": "83e4bb7f56c7fb8b",
    "type": "link in",
    "z": "49e6fe9c14ed777a",
    "name": "link in 4",
    "links": ["727ec4f83c9930a4"],
    "x": 1735,
    "y": 260,
    "wires": [["59e46eeafb4febf7"]]
  },
  {
    "id": "4df1d8fb6c6e0939",
    "type": "mqtt-broker",
    "name": "OVH Mosquitto",
    "broker": "164.132.41.168",
    "port": 1883,
    "clientid": "rpi-gateway-abdellah",
    "autoConnect": true,
    "usetls": false,
    "protocolVersion": 4,
    "keepalive": 60,
    "cleansession": true,
    "autoUnsubscribe": true,
    "birthTopic": "irrigation/rpi/status",
    "birthQos": "1",
    "birthRetain": "true",
    "birthPayload": "{\"status\":\"online\",\"gateway\":\"rpi\"}",
    "willTopic": "irrigation/rpi/status",
    "willQos": "1",
    "willRetain": "true",
    "willPayload": "{\"status\":\"offline\",\"gateway\":\"rpi\"}"
  },
  {
    "id": "0a6617d532e66960",
    "type": "mqtt-broker",
    "name": "OVH Mosquitto",
    "broker": "164.132.41.168",
    "port": 1883,
    "clientid": "rpi-gateway-abdellah",
    "autoConnect": true,
    "usetls": false,
    "protocolVersion": 4,
    "keepalive": 60,
    "cleansession": true,
    "autoUnsubscribe": true,
    "birthTopic": "irrigation/rpi/status",
    "birthQos": "1",
    "birthRetain": "true",
    "birthPayload": "{\"status\":\"online\",\"gateway\":\"rpi\"}",
    "willTopic": "irrigation/rpi/status",
    "willQos": "1",
    "willRetain": "true",
    "willPayload": "{\"status\":\"offline\",\"gateway\":\"rpi\"}"
  }
]
